[
{
    "model": "sessions.session",
    "pk": "9z9c7gz6tcurbbfrean87ic6b58ijbye",
    "fields": {
        "session_data": ".eJxVizsOgzAQBe-ydYS8XvyjCxex1vZajiKlwFAh7h6QaCjnzbwdMi8rTPvxgsjb2uLWZYmfAhMgPLbE-Su_S1zYh5v78D6T-ZaPR-PeztxoLq6agoFTYe08l-ApZacsOfGIRqyMY_JaKZ8N2aB1oFqDUSiEBMcfbRc0xQ:1pAcXt:qPYm5QEPKkf3b37_M8nZ4gal2IX3_CIYu4IjUdeEflE",
        "expire_date": "2023-01-04T19:57:01.012Z"
    }
},
{
    "model": "products.productcategory",
    "pk": 1,
    "fields": {
        "title": "Букеты",
        "slug": "bouquets"
    }
},
{
    "model": "products.productcategory",
    "pk": 2,
    "fields": {
        "title": "Цветы",
        "slug": "flowers"
    }
},
{
    "model": "products.productcomponent",
    "pk": 1,
    "fields": {
        "title": "Красная роза",
        "slug": "red-roze",
        "price": "200.00",
        "new_arrival": 0,
        "total_count": 100,
        "quantity_in_product": 0,
        "quantity_for_sale": 0,
        "quantity_of_sold": 0,
        "available": true
    }
},
{
    "model": "products.productcomponent",
    "pk": 2,
    "fields": {
        "title": "Ромашка",
        "slug": "chamomile",
        "price": "100.00",
        "new_arrival": 0,
        "total_count": 100,
        "quantity_in_product": 0,
        "quantity_for_sale": 0,
        "quantity_of_sold": 0,
        "available": false
    }
},
{
    "model": "products.product",
    "pk": 2,
    "fields": {
        "category": 1,
        "title": "Букет из роз и ромашек",
        "slug": "bouquet-of-roses-and-daisies",
        "preview": "products/previews/our3_YaR6RrP.jpg",
        "price": "0.00",
        "discount": 10,
        "new_price": "0.00",
        "quantity": 1,
        "status": 2
    }
},
{
    "model": "products.productgallery",
    "pk": 2,
    "fields": {
        "product": 2,
        "image": "products/images/our6_e3VUtiK.jpg"
    }
},
{
    "model": "products.productcomposition",
    "pk": 2,
    "fields": {
        "product": 2,
        "component": 1,
        "quantity": 10,
        "price": "0.00"
    }
},
{
    "model": "products.productcomposition",
    "pk": 3,
    "fields": {
        "product": 2,
        "component": 2,
        "quantity": 10,
        "price": "0.00"
    }
},
{
    "model": "users.user",
    "fields": {
        "password": "pbkdf2_sha256$390000$RmZmvQKv56kcNhhvzIhrgU$g/EUB+sXWQ6huJj2YxgTdbhIqGcQWpT4BLHzIPXm+Lo=",
        "last_login": "2022-12-28T18:36:54Z",
        "is_superuser": true,
        "username": "maxim",
        "first_name": "Максим",
        "last_name": "Одинцов",
        "is_staff": true,
        "is_active": true,
        "date_joined": "2022-12-28T18:36:46Z",
        "email": "macsim05.macsim@mail.ru",
        "sex": "M",
        "date_of_birth": "2003-08-02",
        "is_verified": true,
        "groups": [],
        "user_permissions": []
    }
},
{
    "model": "orders.order",
    "pk": 2,
    "fields": {
        "user": [
            "maxim"
        ],
        "amount": "0.00",
        "receipt_method": 1,
        "payment_method": 1,
        "order_status": 3,
        "readiness_status": 1,
        "creation_time": "2022-12-28T18:48:23.251Z",
        "first_name": null,
        "phone": null,
        "email": null,
        "address": null
    }
},
{
    "model": "orders.orderitem",
    "pk": 1,
    "fields": {
        "order": 2,
        "product": 2,
        "quantity": 1,
        "price": "0.00"
    }
},
{
    "model": "admin.logentry",
    "pk": 1,
    "fields": {
        "action_time": "2022-12-28T18:37:27.154Z",
        "user": [
            "maxim"
        ],
        "content_type": [
            "users",
            "user"
        ],
        "object_id": "1",
        "object_repr": "Максим",
        "action_flag": 2,
        "change_message": "[{\"changed\": {\"fields\": [\"First name\", \"Last name\", \"Email\", \"\\u041f\\u043e\\u043b\", \"\\u0414\\u0435\\u043d\\u044c \\u0440\\u043e\\u0436\\u0434\\u0435\\u043d\\u0438\\u044f\", \"\\u041f\\u043e\\u043b\\u044c\\u0437\\u043e\\u0432\\u0430\\u0442\\u0435\\u043b\\u044c \\u0432\\u0435\\u0440\\u0438\\u0444\\u0438\\u0446\\u0438\\u0440\\u043e\\u0432\\u0430\\u043d\"]}}]"
    }
},
{
    "model": "admin.logentry",
    "pk": 2,
    "fields": {
        "action_time": "2022-12-28T18:37:58.499Z",
        "user": [
            "maxim"
        ],
        "content_type": [
            "products",
            "productcategory"
        ],
        "object_id": "1",
        "object_repr": "Букеты",
        "action_flag": 1,
        "change_message": "[{\"added\": {}}]"
    }
},
{
    "model": "admin.logentry",
    "pk": 3,
    "fields": {
        "action_time": "2022-12-28T18:38:08.210Z",
        "user": [
            "maxim"
        ],
        "content_type": [
            "products",
            "productcategory"
        ],
        "object_id": "1",
        "object_repr": "Букеты",
        "action_flag": 2,
        "change_message": "[{\"changed\": {\"fields\": [\"\\u041d\\u0430\\u0437\\u0432\\u0430\\u043d\\u0438\\u0435 \\u043d\\u0430 \\u0430\\u043d\\u0433\\u043b\\u0438\\u0439\\u0441\\u043a\\u043e\\u043c\"]}}]"
    }
},
{
    "model": "admin.logentry",
    "pk": 4,
    "fields": {
        "action_time": "2022-12-28T18:40:07.413Z",
        "user": [
            "maxim"
        ],
        "content_type": [
            "products",
            "productcomponent"
        ],
        "object_id": "1",
        "object_repr": "Красная роза",
        "action_flag": 1,
        "change_message": "[{\"added\": {}}]"
    }
},
{
    "model": "admin.logentry",
    "pk": 5,
    "fields": {
        "action_time": "2022-12-28T18:40:11.982Z",
        "user": [
            "maxim"
        ],
        "content_type": [
            "products",
            "productcomponent"
        ],
        "object_id": "1",
        "object_repr": "Красная роза",
        "action_flag": 2,
        "change_message": "[{\"changed\": {\"fields\": [\"\\u0414\\u043e\\u0441\\u0442\\u0443\\u043f\\u0435\\u043d\"]}}]"
    }
},
{
    "model": "admin.logentry",
    "pk": 6,
    "fields": {
        "action_time": "2022-12-28T18:44:27.858Z",
        "user": [
            "maxim"
        ],
        "content_type": [
            "products",
            "productcomponent"
        ],
        "object_id": "2",
        "object_repr": "Ромашка",
        "action_flag": 1,
        "change_message": "[{\"added\": {}}]"
    }
},
{
    "model": "admin.logentry",
    "pk": 7,
    "fields": {
        "action_time": "2022-12-28T18:46:29.225Z",
        "user": [
            "maxim"
        ],
        "content_type": [
            "products",
            "product"
        ],
        "object_id": "2",
        "object_repr": "Букет из роз и ромашек",
        "action_flag": 1,
        "change_message": "[{\"added\": {}}, {\"added\": {\"name\": \"\\u0418\\u0437\\u043e\\u0431\\u0440\\u0430\\u0436\\u0435\\u043d\\u0438\\u0435\", \"object\": \"ProductGallery object (2)\"}}, {\"added\": {\"name\": \"\\u0421\\u043e\\u0441\\u0442\\u0430\\u0432\", \"object\": \"\\u041a\\u0440\\u0430\\u0441\\u043d\\u0430\\u044f \\u0440\\u043e\\u0437\\u0430 composition for \\u0411\\u0443\\u043a\\u0435\\u0442 \\u0438\\u0437 \\u0440\\u043e\\u0437 \\u0438 \\u0440\\u043e\\u043c\\u0430\\u0448\\u0435\\u043a\"}}, {\"added\": {\"name\": \"\\u0421\\u043e\\u0441\\u0442\\u0430\\u0432\", \"object\": \"\\u0420\\u043e\\u043c\\u0430\\u0448\\u043a\\u0430 composition for \\u0411\\u0443\\u043a\\u0435\\u0442 \\u0438\\u0437 \\u0440\\u043e\\u0437 \\u0438 \\u0440\\u043e\\u043c\\u0430\\u0448\\u0435\\u043a\"}}]"
    }
},
{
    "model": "admin.logentry",
    "pk": 8,
    "fields": {
        "action_time": "2022-12-28T18:46:37.173Z",
        "user": [
            "maxim"
        ],
        "content_type": [
            "products",
            "product"
        ],
        "object_id": "2",
        "object_repr": "Букет из роз и ромашек",
        "action_flag": 2,
        "change_message": "[{\"changed\": {\"fields\": [\"\\u041a\\u043e\\u043b\\u0438\\u0447\\u0435\\u0441\\u0442\\u0432\\u043e \\u043f\\u0440\\u043e\\u0434\\u0443\\u043a\\u0442\\u043e\\u0432\"]}}]"
    }
},
{
    "model": "admin.logentry",
    "pk": 9,
    "fields": {
        "action_time": "2022-12-28T18:48:23.256Z",
        "user": [
            "maxim"
        ],
        "content_type": [
            "orders",
            "order"
        ],
        "object_id": "2",
        "object_repr": "Заказ №2",
        "action_flag": 1,
        "change_message": "[{\"added\": {}}, {\"added\": {\"name\": \"\\u0422\\u043e\\u0432\\u0430\\u0440\", \"object\": \"\\u0422\\u043e\\u0432\\u0430\\u0440 \\u0437\\u0430\\u043a\\u0430\\u0437\\u0430 \\u21162 - \\\"\\u0411\\u0443\\u043a\\u0435\\u0442 \\u0438\\u0437 \\u0440\\u043e\\u0437 \\u0438 \\u0440\\u043e\\u043c\\u0430\\u0448\\u0435\\u043a\\\" \"}}]"
    }
},
{
    "model": "admin.logentry",
    "pk": 10,
    "fields": {
        "action_time": "2022-12-28T19:31:32.787Z",
        "user": [
            "maxim"
        ],
        "content_type": [
            "products",
            "productcategory"
        ],
        "object_id": "2",
        "object_repr": "Цветы",
        "action_flag": 1,
        "change_message": "[{\"added\": {}}]"
    }
},
{
    "model": "admin.logentry",
    "pk": 11,
    "fields": {
        "action_time": "2022-12-28T19:56:00.943Z",
        "user": [
            "maxim"
        ],
        "content_type": [
            "products",
            "productcomponent"
        ],
        "object_id": "2",
        "object_repr": "Ромашка",
        "action_flag": 2,
        "change_message": "[{\"changed\": {\"fields\": [\"\\u041d\\u0430\\u0437\\u0432\\u0430\\u043d\\u0438\\u0435 \\u043d\\u0430 \\u0430\\u043d\\u0433\\u043b\\u0438\\u0439\\u0441\\u043a\\u043e\\u043c\"]}}]"
    }
}
]
